COPYING.txt
ChangeLog.md
MANIFEST.in
README.md
setup.py
doc/Makefile
doc/conf.py
doc/index.rst
doc/make.bat
doc/_build/doctrees/environment.pickle
doc/_build/doctrees/index.doctree
doc/_build/doctrees/guidelines/index.doctree
doc/_build/doctrees/guidelines/optparse.doctree
doc/_build/doctrees/install/index.doctree
doc/_build/doctrees/tutorials/defining_new_commands.doctree
doc/_build/doctrees/tutorials/defining_new_interfaces.doctree
doc/_build/doctrees/tutorials/defining_your_command_driver.doctree
doc/_build/doctrees/tutorials/index.doctree
doc/_build/doctrees/tutorials/organizing_your_repository.doctree
doc/_build/html/.buildinfo
doc/_build/html/index.html
doc/_build/html/objects.inv
doc/_build/html/search.html
doc/_build/html/searchindex.js
doc/_build/html/_sources/index.txt
doc/_build/html/_sources/guidelines/index.txt
doc/_build/html/_sources/guidelines/optparse.txt
doc/_build/html/_sources/install/index.txt
doc/_build/html/_sources/tutorials/defining_new_commands.txt
doc/_build/html/_sources/tutorials/defining_new_interfaces.txt
doc/_build/html/_sources/tutorials/defining_your_command_driver.txt
doc/_build/html/_sources/tutorials/index.txt
doc/_build/html/_sources/tutorials/organizing_your_repository.txt
doc/_build/html/_static/ajax-loader.gif
doc/_build/html/_static/alert_info_32.png
doc/_build/html/_static/alert_warning_32.png
doc/_build/html/_static/basic.css
doc/_build/html/_static/bg-page.png
doc/_build/html/_static/bullet_orange.png
doc/_build/html/_static/comment-bright.png
doc/_build/html/_static/comment-close.png
doc/_build/html/_static/comment.png
doc/_build/html/_static/doctools.js
doc/_build/html/_static/down-pressed.png
doc/_build/html/_static/down.png
doc/_build/html/_static/file.png
doc/_build/html/_static/haiku.css
doc/_build/html/_static/jquery.js
doc/_build/html/_static/minus.png
doc/_build/html/_static/plus.png
doc/_build/html/_static/pygments.css
doc/_build/html/_static/searchtools.js
doc/_build/html/_static/underscore.js
pyqi.egg-info/PKG-INFO
pyqi.egg-info/SOURCES.txt
pyqi.egg-info/dependency_links.txt
pyqi.egg-info/requires.txt
pyqi.egg-info/top_level.txt
